README
setup.cfg
setup.py
pyparma/__init__.py
pyparma/mpz.pxd
pyparma/ppl.cpp
pyparma/ppl.pyx
pyparma/ppl_shim.cc
pyparma/ppl_shim.hh
pyparma/pylong.c
pyparma/pylong.cpp
pyparma/pylong.pxd
pyparma/pylong.pyx
pyparma/types.pxd
pyparma.egg-info/PKG-INFO
pyparma.egg-info/SOURCES.txt
pyparma.egg-info/dependency_links.txt
pyparma.egg-info/top_level.txt
pyparma/utils/__init__.py
pyparma/utils/representations.py