Metadata-Version: 1.1
Name: pyparma
Version: 0.3.3
Summary: Bindings to the parma polyhedra library,                 allowing to use double description from Python
Home-page: https://github.com/haudren/pyparma
Author: Hervé Audren
Author-email: h.audren@aist.go.jp
License: GPL
Platform: UNKNOWN
Classifier: Development Status :: 3 - Alpha
Classifier: Intended Audience :: Developers
Classifier: Intended Audience :: Science/Research
Classifier: Topic :: Scientific/Engineering :: Mathematics
Classifier: License :: OSI Approved :: GNU General Public License (GPL)
Classifier: Programming Language :: Python :: 2.7
